mlir/__init__.py
mlir-0.0.1.dist-info/LICENSE
mlir-0.0.1.dist-info/METADATA
mlir-0.0.1.dist-info/WHEEL
mlir-0.0.1.dist-info/top_level.txt
mlir-0.0.1.dist-info/RECORD
