Metadata-Version: 2.1
Name: mlir
Version: 0.0.1
Summary: mlir
Author: Rin Arakaki
License: MIT License
Project-URL: Repository, http://github.com/rnarkk/mlir.py
Classifier: Programming Language :: Python
Requires-Python: >=3.11
License-File: LICENSE
Provides-Extra: dev
Requires-Dist: pytest >=7.3.0 ; extra == 'dev'
